{"title": "Grow a better jawbone in your ribs", "title_detail": {"type": "text/plain", "language": null, "base": "https://www.sciencedaily.com/rss/matter_energy/biochemistry.xml", "value": "Grow a better jawbone in your ribs"}, "links": [{"rel": "alternate", "type": "text/html", "href": "https://www.sciencedaily.com/releases/2019/03/190318151744.htm"}], "link": "https://www.sciencedaily.com/releases/2019/03/190318151744.htm", "summary": "Researchers have developed a technique to grow custom-fit bone implants to repair jawbone injuries from a patient's own rib.", "summary_detail": {"type": "text/html", "language": null, "base": "https://www.sciencedaily.com/rss/matter_energy/biochemistry.xml", "value": "Researchers have developed a technique to grow custom-fit bone implants to repair jawbone injuries from a patient's own rib."}, "media_thumbnail": [{"url": "https://www.sciencedaily.com/images/2019/03/190318151744-large.jpg", "height": "381", "width": "300"}], "href": "", "published": "Mon, 18 Mar 2019 15:17:44 EDT", "published_parsed": [2019, 3, 18, 19, 17, 44, 0, 77, 0], "id": "https://www.sciencedaily.com/releases/2019/03/190318151744.htm", "guidislink": false}