{"title": "Human images from world's first total-body scanner unveiled", "title_detail": {"type": "text/plain", "language": null, "base": "https://www.sciencedaily.com/rss/health_medicine/medical_devices.xml", "value": "Human images from world's first total-body scanner unveiled"}, "links": [{"rel": "alternate", "type": "text/html", "href": "https://www.sciencedaily.com/releases/2018/11/181119160231.htm"}], "link": "https://www.sciencedaily.com/releases/2018/11/181119160231.htm", "summary": "EXPLORER, the world's first medical imaging scanner that can capture a 3D picture of the whole human body at once, has produced its first scans.", "summary_detail": {"type": "text/html", "language": null, "base": "https://www.sciencedaily.com/rss/health_medicine/medical_devices.xml", "value": "EXPLORER, the world's first medical imaging scanner that can capture a 3D picture of the whole human body at once, has produced its first scans."}, "published": "Mon, 19 Nov 2018 16:02:31 EST", "published_parsed": [2018, 11, 19, 21, 2, 31, 0, 323, 0], "id": "https://www.sciencedaily.com/releases/2018/11/181119160231.htm", "guidislink": false}