{"title": "Fewer Americans think smoking a pack a day poses a great health risk", "title_detail": {"type": "text/plain", "language": null, "base": "https://www.sciencedaily.com/rss/health_medicine/public_health_education.xml", "value": "Fewer Americans think smoking a pack a day poses a great health risk"}, "links": [{"rel": "alternate", "type": "text/html", "href": "https://www.sciencedaily.com/releases/2018/02/180227125719.htm"}], "link": "https://www.sciencedaily.com/releases/2018/02/180227125719.htm", "summary": "About 3 out of 4 Americans agree that smoking cigarettes causes health problems, but public perception of the risks posed by smoking may be declining, according to a new study.", "summary_detail": {"type": "text/html", "language": null, "base": "https://www.sciencedaily.com/rss/health_medicine/public_health_education.xml", "value": "About 3 out of 4 Americans agree that smoking cigarettes causes health problems, but public perception of the risks posed by smoking may be declining, according to a new study."}, "published": "Tue, 27 Feb 2018 12:57:19 EST", "published_parsed": [2018, 2, 27, 17, 57, 19, 1, 58, 0], "id": "https://www.sciencedaily.com/releases/2018/02/180227125719.htm", "guidislink": false}