{"title": "Unequal pain relief at home for dying patients", "title_detail": {"type": "text/plain", "language": null, "base": "https://www.sciencedaily.com/rss/health_medicine/cancer.xml", "value": "Unequal pain relief at home for dying patients"}, "links": [{"rel": "alternate", "type": "text/html", "href": "https://www.sciencedaily.com/releases/2019/03/190322090246.htm"}], "link": "https://www.sciencedaily.com/releases/2019/03/190322090246.htm", "summary": "Pain relief and end of life care is not being provided equally to people with advanced progressive diseases who were at home during their last three months of life, according to a study of 43,000 people who died across England.", "summary_detail": {"type": "text/html", "language": null, "base": "https://www.sciencedaily.com/rss/health_medicine/cancer.xml", "value": "Pain relief and end of life care is not being provided equally to people with advanced progressive diseases who were at home during their last three months of life, according to a study of 43,000 people who died across England."}, "published": "Fri, 22 Mar 2019 09:02:46 EDT", "published_parsed": [2019, 3, 22, 13, 2, 46, 4, 81, 0], "id": "https://www.sciencedaily.com/releases/2019/03/190322090246.htm", "guidislink": false}