{"title": "Scientists identify gene partnerships that promote spinal cord regeneration", "title_detail": {"type": "text/plain", "language": null, "base": "https://www.sciencedaily.com/rss/health_medicine/nervous_system.xml", "value": "Scientists identify gene partnerships that promote spinal cord regeneration"}, "links": [{"rel": "alternate", "type": "text/html", "href": "https://www.sciencedaily.com/releases/2019/03/190306081657.htm"}], "link": "https://www.sciencedaily.com/releases/2019/03/190306081657.htm", "summary": "Scientists have identified gene 'partners' in the axolotl salamander that, when activated, allow the neural tube and associated nerve fibers to functionally regenerate after severe spinal cord damage. Interestingly, these genes are also present in humans, though they are activated in a different manner.", "summary_detail": {"type": "text/html", "language": null, "base": "https://www.sciencedaily.com/rss/health_medicine/nervous_system.xml", "value": "Scientists have identified gene 'partners' in the axolotl salamander that, when activated, allow the neural tube and associated nerve fibers to functionally regenerate after severe spinal cord damage. Interestingly, these genes are also present in humans, though they are activated in a different manner."}, "published": "Wed, 06 Mar 2019 08:16:57 EST", "published_parsed": [2019, 3, 6, 13, 16, 57, 2, 65, 0], "id": "https://www.sciencedaily.com/releases/2019/03/190306081657.htm", "guidislink": false}