{"title": "Fountain of youth for heart health may lie in the gut", "title_detail": {"type": "text/plain", "language": null, "base": "https://www.sciencedaily.com/rss/health_medicine/heart_disease.xml", "value": "Fountain of youth for heart health may lie in the gut"}, "links": [{"rel": "alternate", "type": "text/html", "href": "https://www.sciencedaily.com/releases/2019/03/190319163527.htm"}], "link": "https://www.sciencedaily.com/releases/2019/03/190319163527.htm", "summary": "As our collection of resident gut bacteria changes with age, it increasingly produces harmful metabolites that damage veins and blood vessels, driving disease, a new study suggests.", "summary_detail": {"type": "text/html", "language": null, "base": "https://www.sciencedaily.com/rss/health_medicine/heart_disease.xml", "value": "As our collection of resident gut bacteria changes with age, it increasingly produces harmful metabolites that damage veins and blood vessels, driving disease, a new study suggests."}, "published": "Tue, 19 Mar 2019 16:35:27 EDT", "published_parsed": [2019, 3, 19, 20, 35, 27, 1, 78, 0], "id": "https://www.sciencedaily.com/releases/2019/03/190319163527.htm", "guidislink": false}