{"title": "How the immune system maintains a healthy gut microbiota", "title_detail": {"type": "text/plain", "language": null, "base": "https://www.sciencedaily.com/rss/health_medicine/immune_system.xml", "value": "How the immune system maintains a healthy gut microbiota"}, "links": [{"rel": "alternate", "type": "text/html", "href": "https://www.sciencedaily.com/releases/2019/02/190226112241.htm"}], "link": "https://www.sciencedaily.com/releases/2019/02/190226112241.htm", "summary": "Researchers have uncovered a critical mechanism that controls immune reactions against microorganisms in the intestine. The results of the international study may contribute to the development of new therapies for chronic inflammatory bowel disease.", "summary_detail": {"type": "text/html", "language": null, "base": "https://www.sciencedaily.com/rss/health_medicine/immune_system.xml", "value": "Researchers have uncovered a critical mechanism that controls immune reactions against microorganisms in the intestine. The results of the international study may contribute to the development of new therapies for chronic inflammatory bowel disease."}, "published": "Tue, 26 Feb 2019 11:22:41 EST", "published_parsed": [2019, 2, 26, 16, 22, 41, 1, 57, 0], "id": "https://www.sciencedaily.com/releases/2019/02/190226112241.htm", "guidislink": false}