{"title": "Folliculin mutations disrupt embryo implantation", "title_detail": {"type": "text/plain", "language": null, "base": "https://www.sciencedaily.com/rss/health_medicine/stem_cells.xml", "value": "Folliculin mutations disrupt embryo implantation"}, "links": [{"rel": "alternate", "type": "text/html", "href": "https://www.sciencedaily.com/releases/2019/02/190207075105.htm"}], "link": "https://www.sciencedaily.com/releases/2019/02/190207075105.htm", "summary": "New information is unfolding on the genetic controls of an early turning point in pregnancy -- the changes in an embryo's cells that occur as it prepares to lodge in the wall of the uterus. Understanding what can go wrong with these genetic controls is shedding light on implantation failure, a major cause of human infertility.", "summary_detail": {"type": "text/html", "language": null, "base": "https://www.sciencedaily.com/rss/health_medicine/stem_cells.xml", "value": "New information is unfolding on the genetic controls of an early turning point in pregnancy -- the changes in an embryo's cells that occur as it prepares to lodge in the wall of the uterus. Understanding what can go wrong with these genetic controls is shedding light on implantation failure, a major cause of human infertility."}, "published": "Thu, 07 Feb 2019 07:51:05 EST", "published_parsed": [2019, 2, 7, 12, 51, 5, 3, 38, 0], "id": "https://www.sciencedaily.com/releases/2019/02/190207075105.htm", "guidislink": false}