{"title": "Gene therapy researchers find a viral barcode to cross the blood-brain barrier", "title_detail": {"type": "text/plain", "language": null, "base": "https://www.sciencedaily.com/rss/health_medicine/gene_therapy.xml", "value": "Gene therapy researchers find a viral barcode to cross the blood-brain barrier"}, "links": [{"rel": "alternate", "type": "text/html", "href": "https://www.sciencedaily.com/releases/2018/02/180208230328.htm"}], "link": "https://www.sciencedaily.com/releases/2018/02/180208230328.htm", "summary": "Researchers have discovered a structure on viruses that makes them better at crossing from the bloodstream into the brain \u2013 a key factor for administering gene therapies at lower doses for treating brain and spinal disorders. Experiments also showed decreased liver toxicity.", "summary_detail": {"type": "text/html", "language": null, "base": "https://www.sciencedaily.com/rss/health_medicine/gene_therapy.xml", "value": "Researchers have discovered a structure on viruses that makes them better at crossing from the bloodstream into the brain \u2013 a key factor for administering gene therapies at lower doses for treating brain and spinal disorders. Experiments also showed decreased liver toxicity."}, "published": "Thu, 08 Feb 2018 23:03:28 EST", "published_parsed": [2018, 2, 9, 4, 3, 28, 4, 40, 0], "id": "https://www.sciencedaily.com/releases/2018/02/180208230328.htm", "guidislink": false}