{"title": "Researchers discover a flipping crab feeding on methane seeps", "title_detail": {"type": "text/plain", "language": null, "base": "https://www.sciencedaily.com/rss/plants_animals/marine_biology.xml", "value": "Researchers discover a flipping crab feeding on methane seeps"}, "links": [{"rel": "alternate", "type": "text/html", "href": "https://www.sciencedaily.com/releases/2019/02/190220133539.htm"}], "link": "https://www.sciencedaily.com/releases/2019/02/190220133539.htm", "summary": "Researchers have documented a group of tanner crabs vigorously feeding at a methane seep on the seafloor off British Columbia -- one of the first times a commercially harvested species has been seen using this energy source.", "summary_detail": {"type": "text/html", "language": null, "base": "https://www.sciencedaily.com/rss/plants_animals/marine_biology.xml", "value": "Researchers have documented a group of tanner crabs vigorously feeding at a methane seep on the seafloor off British Columbia -- one of the first times a commercially harvested species has been seen using this energy source."}, "media_thumbnail": [{"url": "https://www.sciencedaily.com/images/2019/02/190220133539-large.jpg", "height": "188", "width": "300"}], "href": "", "published": "Wed, 20 Feb 2019 13:35:39 EST", "published_parsed": [2019, 2, 20, 18, 35, 39, 2, 51, 0], "id": "https://www.sciencedaily.com/releases/2019/02/190220133539.htm", "guidislink": false}