{"title": "Biological mechanism passes on long-term epigenetic 'memories'", "title_detail": {"type": "text/plain", "language": null, "base": "https://www.sciencedaily.com/rss/plants_animals/epigenetics.xml", "value": "Biological mechanism passes on long-term epigenetic 'memories'"}, "links": [{"rel": "alternate", "type": "text/html", "href": "https://www.sciencedaily.com/releases/2016/03/160328133534.htm"}], "link": "https://www.sciencedaily.com/releases/2016/03/160328133534.htm", "summary": "According to epigenetics -- the study of inheritable changes in gene expression not directly coded in our DNA -- our life experiences may be passed on to our children and our children's children. Studies on survivors of traumatic events have suggested that exposure to stress may indeed have lasting effects on subsequent generations. But how exactly are these genetic \"memories\" passed on?", "summary_detail": {"type": "text/html", "language": null, "base": "https://www.sciencedaily.com/rss/plants_animals/epigenetics.xml", "value": "According to epigenetics -- the study of inheritable changes in gene expression not directly coded in our DNA -- our life experiences may be passed on to our children and our children's children. Studies on survivors of traumatic events have suggested that exposure to stress may indeed have lasting effects on subsequent generations. But how exactly are these genetic \"memories\" passed on?"}, "media_thumbnail": [{"url": "https://www.sciencedaily.com/images/2016/03/160328133534-large.jpg", "height": "200", "width": "300"}], "href": "", "published": "Mon, 28 Mar 2016 13:35:34 EDT", "published_parsed": [2016, 3, 28, 17, 35, 34, 0, 88, 0], "id": "https://www.sciencedaily.com/releases/2016/03/160328133534.htm", "guidislink": false}