{"title": "A simple strategy to improve your mood in 12 minutes", "title_detail": {"type": "text/plain", "language": null, "base": "https://www.sciencedaily.com/rss/top/health.xml", "value": "A simple strategy to improve your mood in 12 minutes"}, "links": [{"rel": "alternate", "type": "text/html", "href": "https://www.sciencedaily.com/releases/2019/03/190327112705.htm"}], "link": "https://www.sciencedaily.com/releases/2019/03/190327112705.htm", "summary": "We all have a remedy -- a glass of wine or a piece of chocolate -- for lifting our spirits when we're in a bad mood. Rather than focusing on ways to make ourselves feel better, a team of researchers suggests wishing others well.", "summary_detail": {"type": "text/html", "language": null, "base": "https://www.sciencedaily.com/rss/top/health.xml", "value": "We all have a remedy -- a glass of wine or a piece of chocolate -- for lifting our spirits when we're in a bad mood. Rather than focusing on ways to make ourselves feel better, a team of researchers suggests wishing others well."}, "media_thumbnail": [{"url": "https://www.sciencedaily.com/images/2019/03/190327112705-large.jpg", "height": "209", "width": "300"}], "href": "", "published": "Wed, 27 Mar 2019 11:27:05 EDT", "published_parsed": [2019, 3, 27, 15, 27, 5, 2, 86, 0], "id": "https://www.sciencedaily.com/releases/2019/03/190327112705.htm", "guidislink": false}