{"title": "Does story time with an e-book change how parents and toddlers interact?", "title_detail": {"type": "text/plain", "language": null, "base": "https://www.sciencedaily.com/rss/top/society.xml", "value": "Does story time with an e-book change how parents and toddlers interact?"}, "links": [{"rel": "alternate", "type": "text/html", "href": "https://www.sciencedaily.com/releases/2019/03/190325080459.htm"}], "link": "https://www.sciencedaily.com/releases/2019/03/190325080459.htm", "summary": "Traditional print books may have an edge over e-books when it comes to quality time shared between parents and their children, a new study suggests.", "summary_detail": {"type": "text/html", "language": null, "base": "https://www.sciencedaily.com/rss/top/society.xml", "value": "Traditional print books may have an edge over e-books when it comes to quality time shared between parents and their children, a new study suggests."}, "published": "Mon, 25 Mar 2019 08:04:59 EDT", "published_parsed": [2019, 3, 25, 12, 4, 59, 0, 84, 0], "id": "https://www.sciencedaily.com/releases/2019/03/190325080459.htm", "guidislink": false}