{"title": "Study shows alarming increases of firearm deaths in US school-age children", "title_detail": {"type": "text/plain", "language": null, "base": "https://www.sciencedaily.com/rss/top/society.xml", "value": "Study shows alarming increases of firearm deaths in US school-age children"}, "links": [{"rel": "alternate", "type": "text/html", "href": "https://www.sciencedaily.com/releases/2019/03/190321141922.htm"}], "link": "https://www.sciencedaily.com/releases/2019/03/190321141922.htm", "summary": "From 1999 to 2017, 38,942 US children ages 5 to 18 years old were killed by firearms, averaging more than 2,000 deaths a year. In 2017 alone, 2,462 school-age children were killed by firearms compared to 144 police officers and 1,000 active military worldwide who died in the line of duty. The study finds significant increases that began with an epidemic in 2009, followed by another one in 2014. Each of these epidemics has continued through 2017.", "summary_detail": {"type": "text/html", "language": null, "base": "https://www.sciencedaily.com/rss/top/society.xml", "value": "From 1999 to 2017, 38,942 US children ages 5 to 18 years old were killed by firearms, averaging more than 2,000 deaths a year. In 2017 alone, 2,462 school-age children were killed by firearms compared to 144 police officers and 1,000 active military worldwide who died in the line of duty. The study finds significant increases that began with an epidemic in 2009, followed by another one in 2014. Each of these epidemics has continued through 2017."}, "published": "Thu, 21 Mar 2019 14:19:22 EDT", "published_parsed": [2019, 3, 21, 18, 19, 22, 3, 80, 0], "id": "https://www.sciencedaily.com/releases/2019/03/190321141922.htm", "guidislink": false}